LICENSE
MANIFEST.in
README.rst
setup.py
modeldict/__init__.py
modeldict/base.py
modeldict/memory.py
modeldict/models.py
modeldict/redis.py
modeldict/zookeeper.py
modeldict.egg-info/PKG-INFO
modeldict.egg-info/SOURCES.txt
modeldict.egg-info/dependency_links.txt
modeldict.egg-info/not-zip-safe
modeldict.egg-info/top_level.txt
tests/__init__.py
tests/models.py
tests/test_dict.py
tests/urls.py