Metadata-Version: 1.1
Name: modeldict
Version: 0.3.0
Summary: Dictionary-style access to different types of models.
Home-page: http://github.com/disqus/modeldict/
Author: DISQUS
Author-email: opensource@disqus.com
License: UNKNOWN
Platform: UNKNOWN
Classifier: Intended Audience :: Developers
Classifier: Intended Audience :: System Administrators
Classifier: Operating System :: OS Independent
Classifier: Topic :: Software Development
